rtl/bin2gray.sv
module bin2gray #(
    parameter WIDTH = 4
)(
    input logic [WIDTH-1:0] bin,
    
    output logic [WIDTH-1:0] gray
);
    assign gray = bin ^ (bin >> 1);
endmodule

verif/tb_bin2gray.sv
`timescale 1ns/1ps

module tb_bin2gray;
    parameter WIDTH = 4;

    logic [WIDTH-1:0] bin_in;
    logic [WIDTH-1:0] gray_out;

    logic [WIDTH-1:0] prev_gray;
    logic [WIDTH-1:0] expected;
    logic [WIDTH-1:0] xor_res;
    logic [WIDTH-1:0] gray_last;
    logic [WIDTH-1:0] gray_zero;

    bin2gray #(.WIDTH(WIDTH)) bin2gray_instance (
        .bin(bin_in),
        .gray(gray_out)
    ); 

    initial begin
        $dumpfile("tb_bin2gray.vcd");
        $dumpvars(0, tb_bin2gray);

        prev_gray = 4'b0;
        expected  = 4'b0;
        xor_res   = 4'b0;
        gray_last = 4'b0;
        gray_zero = 4'b0;

        for (int i = 0; i < (2**WIDTH); i++) begin
            bin_in = i; 
            #1;

            expected = i ^ (i >> 1);

            assert (gray_out == expected) 
                else $error("Mismatch at binary %d: Expected %b, Got %b", i, expected, gray_out);

            if (i > 0) begin
                xor_res = gray_out ^ prev_gray;
                assert ($countones(xor_res) == 1) 
                    else $error("Bit-change error at binary %d: More than 1 bit changed!", i);
            end

            prev_gray = gray_out;
        end

        gray_last = (2**WIDTH - 1) ^ ((2**WIDTH - 1) >> 1);
        gray_zero = 4'b0;
        xor_res = gray_last ^ gray_zero;
        
        assert ($countones(xor_res) == 1) 
            else $error("Cyclic property failed during wrap-around!");

        $display("SUCCESS: ALL TESTS PASSED!");
        $finish;
    end
endmodule

tb_bin2gray.vcd
$date
	Mon Jun 15 12:01:24 2026
$end
$version
	Icarus Verilog
$end
$timescale
	1ps
$end
$scope module tb_bin2gray $end
$var wire 4 ! gray_out [3:0] $end
$var parameter 32 " WIDTH $end
$var reg 4 # bin_in [3:0] $end
$var reg 4 $ expected [3:0] $end
$var reg 4 % gray_last [3:0] $end
$var reg 4 & gray_zero [3:0] $end
$var reg 4 ' prev_gray [3:0] $end
$var reg 4 ( xor_res [3:0] $end
$scope module bin2gray_instance $end
$var wire 4 ) bin [3:0] $end
$var wire 4 * gray [3:0] $end
$var parameter 32 + WIDTH $end
$upscope $end
$scope begin $ivl_for_loop0 $end
$var integer 32 , i [31:0] $end
$upscope $end
$upscope $end
$enddefinitions $end
$comment Show the parameter values. $end
$dumpall
b100 +
b100 "
$end
#0
$dumpvars
b0 ,
b0 *
b0 )
b0 (
b0 '
b0 &
b0 %
b0 $
b0 #
b0 !
$end
#1000
b1 !
b1 *
b1 #
b1 )
b1 ,
#2000
b11 !
b11 *
b10 #
b10 )
b10 ,
b1 '
b1 (
b1 $
#3000
b10 !
b10 *
b11 #
b11 )
b11 ,
b11 '
b10 (
b11 $
#4000
b110 !
b110 *
b100 #
b100 )
b100 ,
b10 '
b1 (
b10 $
#5000
b111 !
b111 *
b101 #
b101 )
b101 ,
b110 '
b100 (
b110 $
#6000
b101 !
b101 *
b110 #
b110 )
b110 ,
b111 '
b1 (
b111 $
#7000
b100 !
b100 *
b111 #
b111 )
b111 ,
b101 '
b10 (
b101 $
#8000
b1100 !
b1100 *
b1000 #
b1000 )
b1000 ,
b100 '
b1 (
b100 $
#9000
b1101 !
b1101 *
b1001 #
b1001 )
b1001 ,
b1100 '
b1000 (
b1100 $
#10000
b1111 !
b1111 *
b1010 #
b1010 )
b1010 ,
b1101 '
b1 (
b1101 $
#11000
b1110 !
b1110 *
b1011 #
b1011 )
b1011 ,
b1111 '
b10 (
b1111 $
#12000
b1010 !
b1010 *
b1100 #
b1100 )
b1100 ,
b1110 '
b1 (
b1110 $
#13000
b1011 !
b1011 *
b1101 #
b1101 )
b1101 ,
b1010 '
b100 (
b1010 $
#14000
b1001 !
b1001 *
b1110 #
b1110 )
b1110 ,
b1011 '
b1 (
b1011 $
#15000
b1000 !
b1000 *
b1111 #
b1111 )
b1111 ,
b1001 '
b10 (
b1001 $
#16000
b1000 %
b10000 ,
b1000 '
b1000 (
b1000 $
